{
  "FRANCE": {
    "vs": "PORTUGAL",
    "date":"22/06/2018",
    "score":{"0":"10000", "1":"0"},
    "live":false
  },

  "FRANCE": {
    "vs": "ALLEMAGNE",
    "date":"23/06/2018",
    "score":{"0":"7", "1":"0"},
    "live":false
  },

  "FRANCE": {
    "vs": "BRESIL",
    "date":"24/06/2018",
    "score":{"0":"4", "1":"2"},
    "live":false
  }

[
  {"Maroc":
  { "vs":"Iran",
    "date":"15\/06\/2018",
    "score":[0,1],"live":false}
  },
  {"Portugal":
  {"vs":"Espagne",
    "date":"15\/06\/2018",
    "score":[3,3],
    "live":false}
  },
  {"France":
  {"vs":"Australie",
    "date":"16\/06\/2018",
    "score":[3,3],
    "live":false}
  }
]

}
